[
  {
    "type": "info",
    "text": "%cDownload the React DevTools for a better development experience: https://reactjs.org/link/react-devtools font-weight:bold",
    "location": {
      "url": "https://unpkg.com/react-dom@18/umd/react-dom.development.js",
      "lineNumber": 29904,
      "columnNumber": 18
    }
  },
  {
    "type": "error",
    "text": "Failed to load resource: the server responded with a status of 404 (Not Found)",
    "location": {
      "url": "http://localhost:3000/api/ta/department",
      "lineNumber": 0,
      "columnNumber": 0
    }
  },
  {
    "type": "error",
    "text": "Failed to load resource: the server responded with a status of 404 (Not Found)",
    "location": {
      "url": "http://localhost:3000/api/spatial/layout/catalog",
      "lineNumber": 0,
      "columnNumber": 0
    }
  },
  {
    "type": "debug",
    "text": "[studio-layout] catalog load failed SyntaxError: Unexpected token '<', \"<!DOCTYPE \"... is not valid JSON",
    "location": {
      "url": "http://localhost:3000/spatial/spatialApp.js",
      "lineNumber": 2314,
      "columnNumber": 14
    }
  },
  {
    "type": "error",
    "text": "Failed to load resource: the server responded with a status of 404 (Not Found)",
    "location": {
      "url": "http://localhost:3000/favicon.ico",
      "lineNumber": 0,
      "columnNumber": 0
    }
  },
  {
    "type": "log",
    "text": "workspace payload bytes: 286",
    "location": {
      "url": "http://localhost:3000/spatial/persistence.js",
      "lineNumber": 52,
      "columnNumber": 12
    }
  },
  {
    "type": "log",
    "text": "workspace key \"activePageId\": 25 bytes",
    "location": {
      "url": "http://localhost:3000/spatial/persistence.js",
      "lineNumber": 59,
      "columnNumber": 14
    }
  },
  {
    "type": "log",
    "text": "workspace key \"selectedDeskId\": 9 bytes",
    "location": {
      "url": "http://localhost:3000/spatial/persistence.js",
      "lineNumber": 59,
      "columnNumber": 14
    }
  },
  {
    "type": "log",
    "text": "workspace key \"selectedTab\": 9 bytes",
    "location": {
      "url": "http://localhost:3000/spatial/persistence.js",
      "lineNumber": 59,
      "columnNumber": 14
    }
  },
  {
    "type": "log",
    "text": "workspace key \"scene\": 8 bytes",
    "location": {
      "url": "http://localhost:3000/spatial/persistence.js",
      "lineNumber": 59,
      "columnNumber": 14
    }
  },
  {
    "type": "log",
    "text": "workspace key \"activeGraphLayer\": 8 bytes",
    "location": {
      "url": "http://localhost:3000/spatial/persistence.js",
      "lineNumber": 59,
      "columnNumber": 14
    }
  },
  {
    "type": "log",
    "text": "workspace key \"worldViewMode\": 4 bytes",
    "location": {
      "url": "http://localhost:3000/spatial/persistence.js",
      "lineNumber": 59,
      "columnNumber": 14
    }
  },
  {
    "type": "log",
    "text": "workspace key \"camera\": 45 bytes",
    "location": {
      "url": "http://localhost:3000/spatial/persistence.js",
      "lineNumber": 59,
      "columnNumber": 14
    }
  },
  {
    "type": "log",
    "text": "workspace key \"zoom\": 4 bytes",
    "location": {
      "url": "http://localhost:3000/spatial/persistence.js",
      "lineNumber": 59,
      "columnNumber": 14
    }
  },
  {
    "type": "log",
    "text": "workspace key \"openTraceId\": 4 bytes",
    "location": {
      "url": "http://localhost:3000/spatial/persistence.js",
      "lineNumber": 59,
      "columnNumber": 14
    }
  },
  {
    "type": "log",
    "text": "workspace key \"openReportId\": 4 bytes",
    "location": {
      "url": "http://localhost:3000/spatial/persistence.js",
      "lineNumber": 59,
      "columnNumber": 14
    }
  },
  {
    "type": "log",
    "text": "workspace key \"openTaskId\": 7 bytes",
    "location": {
      "url": "http://localhost:3000/spatial/persistence.js",
      "lineNumber": 59,
      "columnNumber": 14
    }
  },
  {
    "type": "log",
    "text": "intent-state payload bytes: 125",
    "location": {
      "url": "http://localhost:3000/spatial/persistence.js",
      "lineNumber": 52,
      "columnNumber": 12
    }
  },
  {
    "type": "log",
    "text": "intent-state key \"intentState\": 109 bytes",
    "location": {
      "url": "http://localhost:3000/spatial/persistence.js",
      "lineNumber": 59,
      "columnNumber": 14
    }
  },
  {
    "type": "log",
    "text": "studio-state payload bytes: 8667",
    "location": {
      "url": "http://localhost:3000/spatial/persistence.js",
      "lineNumber": 52,
      "columnNumber": 12
    }
  },
  {
    "type": "log",
    "text": "studio-state key \"handoffs\": 8616 bytes",
    "location": {
      "url": "http://localhost:3000/spatial/persistence.js",
      "lineNumber": 59,
      "columnNumber": 14
    }
  },
  {
    "type": "log",
    "text": "studio-state key \"teamBoard\": 25 bytes",
    "location": {
      "url": "http://localhost:3000/spatial/persistence.js",
      "lineNumber": 59,
      "columnNumber": 14
    }
  },
  {
    "type": "log",
    "text": "pages payload bytes: 4671",
    "location": {
      "url": "http://localhost:3000/spatial/persistence.js",
      "lineNumber": 52,
      "columnNumber": 12
    }
  },
  {
    "type": "log",
    "text": "pages key \"pages\": 4620 bytes",
    "location": {
      "url": "http://localhost:3000/spatial/persistence.js",
      "lineNumber": 59,
      "columnNumber": 14
    }
  },
  {
    "type": "log",
    "text": "pages key \"activePageId\": 25 bytes",
    "location": {
      "url": "http://localhost:3000/spatial/persistence.js",
      "lineNumber": 59,
      "columnNumber": 14
    }
  }
]
